agent_squad/__init__.py
agent_squad/orchestrator.py
agent_squad/agents/__init__.py
agent_squad/agents/agent.py
agent_squad/agents/amazon_bedrock_agent.py
agent_squad/agents/anthropic_agent.py
agent_squad/agents/bedrock_flows_agent.py
agent_squad/agents/bedrock_inline_agent.py
agent_squad/agents/bedrock_llm_agent.py
agent_squad/agents/bedrock_translator_agent.py
agent_squad/agents/chain_agent.py
agent_squad/agents/comprehend_filter_agent.py
agent_squad/agents/lambda_agent.py
agent_squad/agents/lex_bot_agent.py
agent_squad/agents/openai_agent.py
agent_squad/agents/strands_agent.py
agent_squad/agents/supervisor_agent.py
agent_squad/classifiers/__init__.py
agent_squad/classifiers/anthropic_classifier.py
agent_squad/classifiers/bedrock_classifier.py
agent_squad/classifiers/classifier.py
agent_squad/classifiers/openai_classifier.py
agent_squad/retrievers/__init__.py
agent_squad/retrievers/amazon_kb_retriever.py
agent_squad/retrievers/retriever.py
agent_squad/shared/__init__.py
agent_squad/shared/user_agent.py
agent_squad/shared/version.py
agent_squad/storage/__init__.py
agent_squad/storage/chat_storage.py
agent_squad/storage/dynamodb_chat_storage.py
agent_squad/storage/in_memory_chat_storage.py
agent_squad/storage/sql_chat_storage.py
agent_squad/types/__init__.py
agent_squad/types/types.py
agent_squad/utils/__init__.py
agent_squad/utils/helpers.py
agent_squad/utils/logger.py
agent_squad/utils/tool.py
agent_squad-1.0.2.dist-info/licenses/LICENSE
agent_squad-1.0.2.dist-info/METADATA
agent_squad-1.0.2.dist-info/WHEEL
agent_squad-1.0.2.dist-info/top_level.txt
agent_squad-1.0.2.dist-info/RECORD
