Metadata-Version: 2.4
Name: agent_squad
Version: 1.0.2
Summary: Agent Squad framework
Home-page: https://github.com/awslabs/agent-squad
Author: Anthony Bernabeu, Corneliu Croitoru
Author-email: brnaba@amazon.com, ccroito@amazon.com
License: Apache License 2.0
Classifier: Programming Language :: Python :: 3
Classifier: License :: OSI Approved :: Apache Software License
Classifier: Operating System :: OS Independent
Requires-Python: >=3.11
License-File: LICENSE
Provides-Extra: aws
Requires-Dist: boto3>=1.36.18; extra == "aws"
Provides-Extra: anthropic
Requires-Dist: anthropic>=0.49.0; extra == "anthropic"
Provides-Extra: openai
Requires-Dist: openai>=1.55.3; extra == "openai"
Provides-Extra: sql
Requires-Dist: libsql-client>=0.3.1; extra == "sql"
Provides-Extra: strands-agents
Requires-Dist: strands-agents>=0.1.6; extra == "strands-agents"
Provides-Extra: all
Requires-Dist: anthropic>=0.40.0; extra == "all"
Requires-Dist: openai>=1.55.3; extra == "all"
Requires-Dist: boto3>=1.36.18; extra == "all"
Requires-Dist: libsql-client>=0.3.1; extra == "all"
Dynamic: license-file
